gui/__init__.py
gui/completer.py
gui/frameLayout.py
gui/genericDialogForm.py
gui/treeModel.py
gui/utility.py
utility/__init__.py
utility/graphScene.py
mor-0.0.2.dist-info/LICENSE
mor-0.0.2.dist-info/METADATA
mor-0.0.2.dist-info/WHEEL
mor-0.0.2.dist-info/top_level.txt
mor-0.0.2.dist-info/RECORD
